.readthedocs.txt
MANIFEST.in
Readme.rst
requirements.txt
setup.py
Flask_Diamond.egg-info/PKG-INFO
Flask_Diamond.egg-info/SOURCES.txt
Flask_Diamond.egg-info/dependency_links.txt
Flask_Diamond.egg-info/not-zip-safe
Flask_Diamond.egg-info/requires.txt
Flask_Diamond.egg-info/top_level.txt
bin/flask-diamond
flask_diamond/__init__.py
flask_diamond/__init__.pyc
flask_diamond/__meta__.py
flask_diamond/facets/__init__.py
flask_diamond/facets/__init__.pyc
flask_diamond/facets/accounts.py
flask_diamond/facets/accounts.pyc
flask_diamond/facets/administration.py
flask_diamond/facets/administration.pyc
flask_diamond/facets/blueprints.py
flask_diamond/facets/blueprints.pyc
flask_diamond/facets/configuration.py
flask_diamond/facets/configuration.pyc
flask_diamond/facets/database.py
flask_diamond/facets/database.pyc
flask_diamond/facets/debugger.py
flask_diamond/facets/debugger.pyc
flask_diamond/facets/email.py
flask_diamond/facets/email.pyc
flask_diamond/facets/forms.py
flask_diamond/facets/forms.pyc
flask_diamond/facets/handlers.py
flask_diamond/facets/handlers.pyc
flask_diamond/facets/logs.py
flask_diamond/facets/logs.pyc
flask_diamond/facets/marshalling.py
flask_diamond/facets/marshalling.pyc
flask_diamond/facets/rest.py
flask_diamond/facets/rest.pyc
flask_diamond/facets/signals.py
flask_diamond/facets/signals.pyc
flask_diamond/facets/task_queue.py
flask_diamond/facets/task_queue.pyc
flask_diamond/facets/webassets.py
flask_diamond/facets/webassets.pyc
flask_diamond/mixins/__init__.py
flask_diamond/mixins/__init__.pyc
flask_diamond/mixins/crud.py
flask_diamond/mixins/crud.pyc
flask_diamond/mixins/marshmallow.py
flask_diamond/mixins/marshmallow.pyc
flask_diamond/models/__init__.py
flask_diamond/models/__init__.pyc
flask_diamond/models/role.py
flask_diamond/models/role.pyc
flask_diamond/models/user.py
flask_diamond/models/user.pyc
flask_diamond/skels/app/.gitignore
flask_diamond/skels/app/.mrbob.ini
flask_diamond/skels/app/.readthedocs.txt
flask_diamond/skels/app/.travis.yml
flask_diamond/skels/app/MANIFEST.in.bob
flask_diamond/skels/app/Makefile.bob
flask_diamond/skels/app/Readme.rst.bob
flask_diamond/skels/app/fabfile.py.bob
flask_diamond/skels/app/requirements.txt.bob
