Metadata-Version: 1.1
Name: Flask-Diamond
Version: 0.5.1
Summary: Flask-Diamond provides some opinions about data-centric Internet applications and systems. Flask-Diamond is a batteries-included Flask framework, sortof like Django but radically decomposable.
Home-page: http://flask-diamond.readthedocs.org
Author: Ian Dennis Miller
Author-email: iandennismiller@gmail.com
License: MIT
Platform: UNKNOWN
Classifier: Development Status :: 4 - Beta
Classifier: Framework :: Flask
Classifier: Intended Audience :: Developers
Classifier: Intended Audience :: Science/Research
Classifier: License :: OSI Approved :: MIT License
Classifier: Operating System :: POSIX
Classifier: Operating System :: MacOS :: MacOS X
Classifier: Programming Language :: Python :: 2.7
Classifier: Programming Language :: Python :: 3.4
Classifier: Programming Language :: Python :: 3.5
Classifier: Topic :: Internet :: WWW/HTTP
